muscle/__init__.py
muscle/main.py
muscle/controller/__init__.py
muscle/controller/controller.py
muscle/model/__init__.py
muscle/model/model.py
muscle/util/__init__.py
muscle/util/database.py
muscle/util/errors.py
muscle/util/format.py
muscle/view/__init__.py
muscle/view/cli.py
muscle/view/options.py
muscle_xz18-0.1.1.dist-info/LICENSE
muscle_xz18-0.1.1.dist-info/METADATA
muscle_xz18-0.1.1.dist-info/WHEEL
muscle_xz18-0.1.1.dist-info/entry_points.txt
muscle_xz18-0.1.1.dist-info/top_level.txt
muscle_xz18-0.1.1.dist-info/RECORD
