Metadata-Version: 2.1
Name: muscle-xz18
Version: 0.1.1
Summary: weight lifting tracking app
Home-page: https://github.com/xz18/muscle
Author: xz18
License: UNKNOWN
Project-URL: Bug Report, https://github.com/xz18/muscle/issues
Project-URL: Source Code, https://github.com/xz18/muscle
Platform: UNKNOWN
Classifier: Programming Language :: Python :: 3.5
Classifier: Programming Language :: Python :: 3.6
Classifier: Programming Language :: Python :: 3.7
Classifier: License :: OSI Approved :: GNU General Public License v3 (GPLv3)
Classifier: Operating System :: POSIX :: Linux
Requires-Python: >=3.5
